tgidproviders
