Metadata-Version: 1.0
Name: tgidproviders
Version: 0.2
Summary: A collection of Identity providers for Turbogears
Home-page: http://code.google.com/p/tgidproviders
Author: Ken Kuhlman and contributors
Author-email: tgidproviders@redlagoon.net
License: MIT
Download-URL: http://code.google.com/p/tgidproviders/downloads/list
Keywords: turbogears.identity.provider
Platform: UNKNOWN
Classifier: Development Status :: 3 - Alpha
Classifier: Operating System :: OS Independent
Classifier: Programming Language :: Python
Classifier: Topic :: Software Development :: Libraries :: Python Modules
Classifier: Framework :: TurboGears
Classifier: Framework :: TurboGears :: Widgets
